fastsdcpu/__init__.py
fastsdcpu/app.py
fastsdcpu/app_settings.py
fastsdcpu/constants.py
fastsdcpu/context.py
fastsdcpu/controlnet.py
fastsdcpu/gguf_diffusion.py
fastsdcpu/image_saver.py
fastsdcpu/lora.py
fastsdcpu/safety_checker.py
fastsdcpu/state.py
fastsdcpu/tiny_autoencoder.py
fastsdcpu/annotators/__init__.py
fastsdcpu/annotators/canny_control.py
fastsdcpu/annotators/control_interface.py
fastsdcpu/annotators/depth_control.py
fastsdcpu/annotators/image_control_factory.py
fastsdcpu/annotators/lineart_control.py
fastsdcpu/annotators/mlsd_control.py
fastsdcpu/annotators/normal_control.py
fastsdcpu/annotators/pose_control.py
fastsdcpu/annotators/shuffle_control.py
fastsdcpu/annotators/softedge_control.py
fastsdcpu/api/__init__.py
fastsdcpu/api/dto.py
fastsdcpu/api/mcp_server.py
fastsdcpu/api/web.py
fastsdcpu/models/__init__.py
fastsdcpu/models/device.py
fastsdcpu/models/images.py
fastsdcpu/models/interface_types.py
fastsdcpu/models/lcmdiffusion_setting.py
fastsdcpu/models/sdcpp.py
fastsdcpu/models/settings.py
fastsdcpu/models/upscale.py
fastsdcpu/pipelines/__init__.py
fastsdcpu/pipelines/lcm/__init__.py
fastsdcpu/pipelines/lcm/lora.py
fastsdcpu/pipelines/lcm/text_to_image.py
fastsdcpu/pipelines/openvino/__init__.py
fastsdcpu/pipelines/openvino/ov_hc_stablediffusion_pipeline.py
fastsdcpu/pipelines/openvino/stable_diffusion_engine.py
fastsdcpu/upscaler/__init__.py
fastsdcpu/upscaler/aura_sr.py
fastsdcpu/upscaler/aura_sr_upscale.py
fastsdcpu/upscaler/edsr_upscale_onnx.py
fastsdcpu/upscaler/tiled_upscale.py
fastsdcpu/utils/__init__.py
fastsdcpu/utils/device.py
fastsdcpu/utils/file.py
fastsdcpu/utils/image.py
fastsdcpu/utils/paths.py
fastsdcpu_pip-0.1.5.dist-info/licenses/LICENSE
fastsdcpu_pip-0.1.5.dist-info/licenses/THIRD-PARTY-LICENSES
fastsdcpu_pip-0.1.5.dist-info/METADATA
fastsdcpu_pip-0.1.5.dist-info/WHEEL
fastsdcpu_pip-0.1.5.dist-info/top_level.txt
fastsdcpu_pip-0.1.5.dist-info/RECORD
